mopsy/__init__.py
mopsy/adders.py
mopsy/checkutils.py
mopsy/helpers.py
mopsy/mops.py
mopsy/nops.py
mopsy/sops.py
mopsy/utils.py
mopsy-0.3.0.dist-info/LICENSE.txt
mopsy-0.3.0.dist-info/METADATA
mopsy-0.3.0.dist-info/WHEEL
mopsy-0.3.0.dist-info/top_level.txt
mopsy-0.3.0.dist-info/RECORD
