Metadata-Version: 2.1
Name: mopsy
Version: 0.3.0
Summary: Matrix operations for numpy and scipy
Home-page: https://github.com/jkanche/mopsy
Author: jkanche
Author-email: jayaram.kancherla@gmail.com
License: MIT
Project-URL: Documentation, https://github.com/jkanche/mopsy
Platform: any
Classifier: Development Status :: 4 - Beta
Classifier: Programming Language :: Python
Requires-Python: >=3.9
License-File: LICENSE.txt
Requires-Dist: importlib-metadata; python_version < "3.8"
Requires-Dist: numpy
Requires-Dist: scipy<1.13.0; python_version <= "3.9"
Requires-Dist: scipy; python_version > "3.9"
Provides-Extra: testing
Requires-Dist: setuptools; extra == "testing"
Requires-Dist: pytest; extra == "testing"
Requires-Dist: pytest-cov; extra == "testing"
